bin/__init__.py
bin/kck_http.py
kck/__init__.py
kck/version.py
kck/lib/__init__.py
kck/lib/cassandra_actor.py
kck/lib/decorators.py
kck/lib/err.py
kck/lib/exceptions.py
kck/lib/framework_actor.py
kck/lib/hints.py
kck/lib/http_service.py
kck/lib/kck_auth.py
kck/lib/kck_cache.py
kck/lib/kck_data.py
kck/lib/kck_database.py
kck/lib/kck_primer.py
kck/lib/kck_updater.py
kck/lib/log.py
kck/lib/yaml_primer.py
kck/lib/yaml_reader.py
kck/lib/yaml_updater.py
kck/test/__init__.py
kck/test/cache.py
kck/test/test_case.py
kck-0.6.3.data/data/README.md
kck-0.6.3.dist-info/LICENSE.txt
kck-0.6.3.dist-info/METADATA
kck-0.6.3.dist-info/WHEEL
kck-0.6.3.dist-info/entry_points.txt
kck-0.6.3.dist-info/top_level.txt
kck-0.6.3.dist-info/RECORD
