Metadata-Version: 2.1
Name: kck
Version: 0.6.3
Summary: A high-performance framework for dynamic data
Home-page: https://gitlab.com/frameworklabs/kck
Author: Framework Labs
Author-email: fred@frameworklabs.us
License: MIT
Keywords: performance-oriented data pipeline framework
Platform: UNKNOWN
Classifier: Development Status :: 2 - Pre-Alpha
Classifier: Intended Audience :: Developers
Classifier: Topic :: Software Development :: Libraries :: Python Modules
Classifier: Topic :: Internet :: WWW/HTTP :: HTTP Servers
Classifier: Topic :: Database :: Front-Ends
Classifier: License :: OSI Approved :: MIT License
Classifier: Programming Language :: Python :: 3.5
Requires-Dist: PyYAML (>=3.13)
Requires-Dist: python-dateutil (>=2.2)
Requires-Dist: cassandra-driver (>=3.13)
Requires-Dist: SQLAlchemy (>=1.1.11)
Requires-Dist: psycopg2 (>=2.7.5)
Requires-Dist: jsonpath-ng (>=1.4.2)
Requires-Dist: simple-settings (>=0.13.0)
Requires-Dist: jwt (>=0.6.1)
